{
    "header": {
        "nav": {
            "home": "Головна",
            "services": "Послуги",
            "portfolio": "Портфоліо",
            "about": "Про нас",
            "partnership": "Партнерство",
            "blog": "Блог",
            "contacts": "Контакти"
        }
    },
    "cookie": {
        "para": "Ми використовуємо файли cookie. Вони забезпечують безперебійну роботу сайту, аналітичних, рекламних та соціальних інструментів. Детальніше у",
        "ref": "Політиці конфіденційності.",
        "button": "Приймаю"
    },
    "footer": {
        "links": {
            "sitemap": "Карта сайту",
            "terms": "Умови використання",
            "privacy": "Політика конфіденційності",
            "cookies": "Файли Cookies"
        }
    },
    "mainHero": {
        "header": "Fullstack Innovations",
        "description": "Розробка сучасних сайтів <span>та комплексне</span> просування вашого бізнесу <span>в лідери</span>",
        "contactButton": "Зв’язатися з нами",
        "getOffer": "отримати",
        "offer": "пропозицію",
        "developedSitesLabel": "Кількість розроблених сайтів",
        "developedSitesCount": "200 +",
        "marquee": {
            "textItems1": [
                "Лендінг",
                "Багатосторінковий",
                "Інтернет-магазин",
                "2D дизайн",
                "3D моделювання",
                "Розробка логотипів",
                "Google Ads",
                "SEO-просування",
                "UI/UX дизайн",
                "Сайт для доставки",
                "Бізнес сайт",
                "Мобільні застосунки",
                "Лендінг",
                "Багатосторінковий",
                "Інтернет-магазин"
            ],
            "textItems2": [
                "FULLSTACK-INNOVATIONS",
                "FULLSTACK-INNOVATIONS",
                "FULLSTACK-INNOVATIONS",
                "FULLSTACK-INNOVATIONS",
                "FULLSTACK-INNOVATIONS",
                "FULLSTACK-INNOVATIONS",
                "FULLSTACK-INNOVATIONS",
                "FULLSTACK-INNOVATIONS",
                "FULLSTACK-INNOVATIONS",
                "FULLSTACK-INNOVATIONS",
                "FULLSTACK-INNOVATIONS"
            ]
        }
    },
    "mainSecond": {
        "title": "Ми вам потрібні якщо",
        "buttonText": "Розкажіть про свій проєкт",
        "listItems": [
            {
                "title": "Немає сайту або думаєте над його створенням",
                "description": "Ви відкрили новий бізнес або напрямок і не готові інвестувати в перший сайт десятки тисяч доларів, краще цю суму вкласти в розвиток бізнесу, але і зробити сайт за 300$ не є рішенням, розумієте яка буде якість. Ми якраз золота середина і не використовуємо дорогі технології, нам вдається дати якість топових сайтів за адекватні гроші."
            },
            {
                "title": "Застарілий дизайн та функціонал сайту",
                "description": "Ви відкрили новий бізнес або напрямок і не готові інвестувати в перший сайт десятки тисяч доларів, краще цю суму вкласти в розвиток бізнесу, але і зробити сайт за 300$ не є рішенням, розумієте яка буде якість. Ми якраз золота середина і не використовуємо дорогі технології, нам вдається дати якість топових сайтів за адекватні гроші."
            },
            {
                "title": "Змінити платформу",
                "description": "Ви відкрили новий бізнес або напрямок і не готові інвестувати в перший сайт десятки тисяч доларів, краще цю суму вкласти в розвиток бізнесу, але і зробити сайт за 300$ не є рішенням, розумієте яка буде якість. Ми якраз золота середина і не використовуємо дорогі технології, нам вдається дати якість топових сайтів за адекватні гроші."
            },
            {
                "title": "Створення дизайн-упаковки для бізнесу",
                "description": "Ви відкрили новий бізнес або напрямок і не готові інвестувати в перший сайт десятки тисяч доларів, краще цю суму вкласти в розвиток бізнесу, але і зробити сайт за 300$ не є рішенням, розумієте яка буде якість. Ми якраз золота середина і не використовуємо дорогі технології, нам вдається дати якість топових сайтів за адекватні гроші."
            }
        ]
    },
    "mainServices": {
        "title": "Послуги",
        "subtitle": "Fullstack Innovations",
        "tabs": [
            {
                "label": "Всі послуги",
                "value": "all"
            },
            {
                "label": "Веб-розробка",
                "value": "web-development"
            },
            {
                "label": "SEO просування",
                "value": "seo"
            },
            {
                "label": "Контекстна реклама",
                "value": "ads"
            },
            {
                "label": "Мобільні застосунки",
                "value": "mobile-apps"
            },
            {
                "label": "2D дизайн",
                "value": "design"
            },
            {
                "label": "3D моделювання",
                "value": "modeling"
            }
        ],
        "costLabel": "Вартість",
        "deadlineLabel": "Термін реалізації",
        "detailsButton": "Детальніше",
        "services": [
            {
                "id": 1,
                "name": "Лендінг",
                "image": "/images/MainServices/landing.png",
                "h1": "Лендінг",
                "p": "до 20 робочих днів",
                "buttonText": "від 1 300$",
                "imageClass": "landingImage"
            },
            {
                "id": 2,
                "name": "Багатосторінковий",
                "image": "/images/MainServices/multipage.png",
                "h1": "Багатосторінковий",
                "p": "до 35 робочих днів",
                "buttonText": "від 2 000$",
                "imageClass": "multipageImage"
            },
            {
                "id": 3,
                "name": "Інтернет-магазин",
                "image": "/images/MainServices/online-store.png",
                "h1": "Інтернет-магазин",
                "p": "до 20 робочих днів",
                "buttonText": "від 2 000$",
                "imageClass": "onlineStoreImage"
            },
            {
                "id": 4,
                "name": "Сайт для доставки",
                "image": "/images/MainServices/delivery-site.png",
                "h1": "Сайт для доставки",
                "p": "до 20 робочих днів",
                "buttonText": "від 2 000$",
                "imageClass": "deliverySiteImage"
            },
            {
                "id": 5,
                "name": "Бізнес сайт",
                "image": "/images/MainServices/business-site.png",
                "h1": "Бізнес сайт",
                "p": "до 20 робочих днів",
                "buttonText": "від 1 300$",
                "imageClass": "businessSiteImage"
            },
            {
                "id": 6,
                "name": "Мобільні застосунки",
                "image": "/images/MainServices/mobile-apps.png",
                "h1": "Мобільні застосунки",
                "p": "до 35 робочих днів",
                "buttonText": "від 2 000$",
                "imageClass": "mobileAppsImage"
            },
            {
                "id": 7,
                "name": "Google Ads",
                "image": "/images/MainServices/google-ads.png",
                "h1": "Google Ads",
                "p": "до 20 робочих днів",
                "buttonText": "від 2 000$",
                "imageClass": "googleAdsImage"
            },
            {
                "id": 8,
                "name": "SEO-просування",
                "image": "/images/MainServices/seo.png",
                "h1": "SEO-просування",
                "p": "до 20 робочих днів",
                "buttonText": "від 1 300$",
                "imageClass": "seoImage"
            },
            {
                "id": 9,
                "name": "2D моделювання",
                "image": "/images/MainServices/3d-modeling.png",
                "h1": "2D моделювання",
                "p": "до 20 робочих днів",
                "buttonText": "від 1 300$",
                "imageClass": "modeling2DImage"
            },
            {
                "id": 10,
                "name": "3D моделювання",
                "image": "/images/MainServices/3d-modeling.png",
                "h1": "3D моделювання",
                "p": "до 35 робочих днів",
                "buttonText": "від 2 000$",
                "imageClass": "modeling3DImage"
            }
        ]
    },
    "ourPortfolioSlider": {
        "title": "Наше портфоліо",
        "buttonText": "Розкажіть про свій проект"
    },
    "aboutHero": {
        "title": "Fullstack Innovations<br />— це унікальна агенція",
        "buttonText": "Розкажіть про свій проект",
        "paragraphs": [
            "Ми - команда професіоналів у галузі веб-розробки та інновацій, яка готова перетворити ваші концепції в успішні та прибуткові проєкти. З кінця 2021 року ми вже реалізували понад 75 успішних веб-сайтів, що свідчить про наш високий рівень експертизи та професіоналізму.",
            "Наш підхід базується на індивідуальному відношенні до кожного клієнта, забезпечуючи розробку сучасних, продуктивних та унікальних веб-рішень. Ми однозначно враховуємо останні тренди та вимоги галузі, щоб надати вашому проєкту конкурентні переваги."
        ],
        "stats": [
            {
                "value": "75",
                "label": "Виконаних проектів"
            },
            {
                "value": "25",
                "label": "Досвідчених спеціалістів"
            },
            {
                "value": "2",
                "label": "Роки досвіду"
            },
            {
                "value": "99%",
                "label": "Задоволених клієнтів"
            }
        ]
    },
    "partnershipCards": {
        "title": "Ми відкриті до партнерських можливостей з однодумцями - компаніями чи окремими особами. Отже, як ми бачимо, партнерство з нами може бути цікавим для:",
        "cards": [
            {
                "title": "Засновники стартапів",
                "description": "Коли вигідно використовувати наші ресурси та експертизу в обмін на частки для розвитку спільного бізнесу"
            },
            {
                "title": "Власники бізнесу",
                "description": "Яким наша експертиза є прибутковою і які можуть надати нам низку переваг у продажу наших послуг"
            },
            {
                "title": "Партнерські продавці",
                "description": "Які зацікавлені в продажу наших програмних рішень і послуг та отриманні комісії з продажів"
            }
        ]
    },
    "partnershipHero": {
        "h1": "Партнерство",
        "para": "«Бізнес — це гра партнерства. Ті, хто добре їх формує, досягнуть успіху, а ті, хто ні, залишаться позаду» — Білл Гейтс",
        "button": "Зв’язатися з нами"
    },
    "partnershipOptions": {
        "title": "Варіанти партнерства",
        "para": "Ми можемо надати вам ряд перевірених варіантів партнерства виберіть для досягнення своїх бізнес-цілей:",
        "cards": [
            {
                "title": "Акціонування",
                "para": "Партнерські тарифи та знижки дозволяють істотно знизити вартість розробка та супровід програмного забезпечення в обмін на акції компанії."
            },
            {
                "title": "Спільна компанія",
                "para": "Вигідно для тих, хто шукає партнера з розробки програмного забезпечення наш досвід для створення дочірньої компанії або нового бізнесу разом."
            },
            {
                "title": "Спеціалізований центр розробки (DDC)",
                "para": "Для тих, хто хоче відкрити DDC як власну юридичну особу в Україні отримати всі переваги аутсорсингу виключно для своїх цілей відкриття бізнесу з використанням нашого досвіду та знань."
            },
            {
                "title": "Партнерство з продажу",
                "para": "Ідеально підходить для незалежних продавців або сторонніх компаній, які мають своїх клієнтів, шукаючи постачальника послуг, який бере повну вартість відповідальність за якість і своєчасність доставки."
            }
        ]
    },
    "partnershipBenefits": {
        "title": "Можливості та переваги для партнерів",
        "para": "Враховуючи новий досвід, ми віримо в досягнення більшого успіху та досягнення нових висот завдяки співпраці та співпраці. Оскільки для цього є цілий ряд причин, зокрема:",
        "benefits": [
            {
                "title": "Доступ до нових ринків",
                "para": "Завдяки партнерству компанії отримують доступ до нових ринків і баз клієнтів, яких вони, можливо, не змогли досягти самостійно."
            },
            {
                "title": "Економія коштів",
                "para": "Спільне використання ресурсів і витрат для створення потенційних клієнтів з іншими через партнерство економічно ефективніше, ніж генерування їх самостійно."
            },
            {
                "title": "Конкурентна перевага",
                "para": "Партнерство дає компаніям конкурентну перевагу завдяки поєднанню сильних сторін і досвіду, щоб запропонувати клієнтам унікальну ціннісну пропозицію."
            },
            {
                "title": "Розширені можливості",
                "para": "Партнерство з іншою компанією дозволяє кожному з нас розширити наші можливості, отримуючи доступ до нових технологій або ресурсів, яких ми могли б не мати інакше."
            },
            {
                "title": "Збільшений дохід",
                "para": "Партнерство веде до збільшення прибутку за рахунок нових каналів продажів, розширення клієнтської бази та доступу до нових продуктів або послуг."
            },
            {
                "title": "Зниження ризику",
                "para": "Партнерство допомагає пом’якшити ризик, розділяючи його з іншими, а не несучи його поодинці, відкриваючи нові шляхи для прискорення зростання та підвищення успіху."
            }
        ]
    },
    "tellAboutUs": {
        "title": "Що кажуть<br />клієнти про нас",
        "buttonText": "Залишити відгук",
        "description": "Ми розробляємо, створюємо та супроводжуємо it-продукти з початку 2012 року. Ми можемо скористатися послугами нового циклу - від планування та ідей до запуску продукту.",
        "reviews": [
            {
                "rating": 4,
                "text": "Завдяки підтримці Codeks веб-сайт клієнта працював ідеально, а клієнти могли легко розміщувати замовлення на платформі. Codeks ефективно та швидко виправили помилки попередніх розробників. Професіоналізм та орієнтованість на клієнта від цього постачальника послуг були зразковими.",
                "name": "Діана Кравець",
                "position": "CEO",
                "date": "15.08.2023"
            },
            {
                "rating": 5,
                "text": "Codeks поставили видатний продукт, який перевершив наші очікування. Їхня увага до деталей та відданість якості зробили весь процес гладким та ефективним. Ми дуже рекомендуємо їхні послуги!",
                "name": "Олег Павленко",
                "position": "CTO",
                "date": "20.09.2023"
            },
            {
                "rating": 3,
                "text": "Співпраця з Codeks стала переломним моментом для нашого бізнесу. Вони надали інноваційні рішення та чудову підтримку протягом усього проєкту. Ми з нетерпінням чекаємо на подальшу співпрацю з ними!",
                "name": "Аліна Мельник",
                "position": "Project Manager",
                "date": "10.10.2023"
            },
            {
                "rating": 3,
                "text": "Співпраця з Codeks стала переломним моментом для нашого бізнесу. Вони надали інноваційні рішення та чудову підтримку протягом усього проєкту. Ми з нетерпінням чекаємо на подальшу співпрацю з ними!",
                "name": "Аліна Мельник",
                "position": "Project Manager",
                "date": "10.10.2023"
            }
        ],
        "modalFeedback": {
            "title": "Відгук або пропозиція щодо роботи",
            "subtitle": "Нам важлива, ваша думка",
            "labels": {
                "name": "Імя",
                "email": "Емейл",
                "message": "Відгук або пропозиція",
                "feedbackType": "Ваша оцінка"
            },
            "errors": {
                "nameRequired": "Заповніть ім'я",
                "emailRequired": "Заповніть пошту",
                "emailInvalid": "Введіть коректний E-mail",
                "feedbackTypeRequired": "Виберіть оцінку",
                "messageRequired": "Заповніть відгук або пропозицію"
            },
            "feedbackOptions": [
                "1 — Погано",
                "2 — Можливо краще",
                "3 — Терпимо",
                "4 — Добре",
                "5 — Відмінно"
            ],
            "submitButton": "Відправити"
        }
    },
    "worldMapPartnership": {
        "title": "Клієнти зі всього світу",
        "getOffer": "отримати",
        "offer": "пропозицію"
    },
    "contactUs": {
        "h1": "Contact Us",
        "para": "FullStack-Innovations — це компанія повного циклу, що спеціалізується на розробці сучасних, високопродуктивних та SEO-оптимізованих веб-рішень. Ми реалізували понад 200 проєктів і продовжуємо бути надійним технологічним партнером для клієнтів із США, Канади, Іспанії, Італії, Люксембургу, Австралії та інших країн."
    },
    "contactUsForm": {
        "title": "Зв’яжіться з нами для розрахунку вартості",
        "fields": {
            "name": "Ваше ім’я",
            "email": "Ваш Email",
            "phone": "Ваш мобільний телефон",
            "message": "Яке бізнес-рішення Вас цікавить?",
            "policy": "Я приймаю",
            "policyRef": "Політику конфіденційності"
        },
        "errors": {
            "name": "Заповніть ім’я",
            "email": "Заповніть пошту",
            "emailInvalid": "Введіть коректний Email",
            "phone": "Введіть коректний номер телефону",
            "message": "Введіть повідомлення",
            "policy": "Погодьтеся з політикою конфіденційності",
            "method": "Виберіть спосіб зв’язку"
        },
        "charLimitMessage": "Досягнуто максимуму 500 символів",
        "methodLabel": "Виберіть зручний спосіб зв’язку",
        "methods": {
            "telegram": "Telegram",
            "whatsapp": "WhatsApp",
            "viber": "Viber",
            "phone": "Phone",
            "email": "Email"
        },
        "submitButton": "Надіслати заявку",
        "successMessage": "Ваше повідомлення успішно надіслано. Дякуємо!"
    },
    "portfolioHero": {
        "title": "Портфоліо",
        "buttonText": "Зв’язатися з нами",
        "description": "“Business is a game of partnerships. Those who form them well will succeed, those who do not will be left behind” — Bill Gates"
    },
    "servicesHero": {
        "title": "Послуги",
        "buttonText": "Зв’язатися з нами",
        "description": "“Business is a game of partnerships. Those who form them well will succeed, those who do not will be left behind” — Bill Gates"
    },
    "servicesThird": {
        "title": "Чи вірите ви в найм професіоналів?",
        "buttonText": "Зв’язатися з нами",
        "description": "Ми — команда із значним досвідом у розробці індивідуальних програмних інженерних рішень щодо веб-сайтів, використовуючи різноманітні технології. Наші експерти володіють різнобічним стеком, включаючи JavaScript, Python, PHP, та використовують фреймворки, такі як React, Django, Next.js та Laravel.<br /> <br />Ми ставимо перед собою важливі завдання забезпечити стабільність та продуктивність для кожного проєкту, використовуючи оптимізований код та передові техніки кешування, для того, щоб забезпечити швидке завантаження сторінок та ефективну роботу веб-сайтів."
    },
    "aboutPeopleSlider": {
        "title": "Обличчя компанії Fullstack Innovations",
        "people": [
            {
                "name": "Діана Кравець",
                "position": "Team manager",
                "image": "/images/first-person.png"
            },
            {
                "name": "Дарья Клименко",
                "position": "Sales Manager",
                "image": "/images/second-person.png"
            },
            {
                "name": "Bладислав Кириленко",
                "position": "Senior HR Generalist",
                "image": "/images/third-person.png"
            },
            {
                "name": "Аліна Маренюк",
                "position": "Project manager",
                "image": "/images/fourth-person.png"
            },
            {
                "name": "Кирилл Павленко",
                "position": "Business Analyst",
                "image": "/images/fifth-person.png"
            }
        ]
    },
    "aboutServicesHero": {
        "title": "Послуги<br />Fullstack Innovations",
        "tabs": [
            {
                "label": "Веб-сайти",
                "value": "websites"
            },
            {
                "label": "Дизайн",
                "value": "design"
            },
            {
                "label": "Розробка",
                "value": "development"
            },
            {
                "label": "Маркетинг",
                "value": "marketing"
            }
        ],
        "services": {
            "websites": [
                "UI/UX дизайн",
                "2D дизайн"
            ],
            "design": [
                "UI/UX дизайн",
                "3D моделювання",
                "2D дизайн",
                "Маркетинг"
            ],
            "development": [
                "Розробка логіки"
            ],
            "marketing": [
                "Маркетинг"
            ]
        }
    },
    "blogContent": {
        "readMore": "Детально",
        "prevButton": "Попередня стаття",
        "nextButton": "Наступна стаття"
    },
    "chooseUs": {
        "title": "Чому<br />обирають нас?",
        "items": [
            {
                "number": "#1",
                "subtitle": "Клієнтоорієнтованість",
                "description": "Глибоке розуміння бізнесу – це наша перевага. Ми спеціалізуємося на створенні веб-сайтів, з важелем на конверсії та продажі."
            },
            {
                "number": "#2",
                "subtitle": "Передові підходи і технології",
                "description": "Наша команда впроваджуємо передові технології для перетворення Вашого веб-сайту в сучасну та інноваційну цифрову платформу."
            },
            {
                "number": "#3",
                "subtitle": "Якісне та швидке виконання",
                "description": "Висока ефективність та швидкість – це основа успіху у співпраці з нами. Індивідуальний підхід до кожного проєкту гарантований!"
            },
            {
                "number": "#4",
                "subtitle": "Креативність",
                "description": "Кожен сайт - це унікальний шедевр мистецтва. Наш креативний дизайн привертає увагу і вражає своїми унікальними інноваціями."
            },
            {
                "number": "#5",
                "subtitle": "Готовність до викликів",
                "description": "Ми гарантуємо результативні рішення завдань та індивідуальний дизайн для Вашого сайту. Сучасні технології у кожному проєкті!"
            },
            {
                "number": "#6",
                "subtitle": "Ретельне тестування рішень",
                "description": "Ваш успіх полягає в наших надійних технологіях. Ми тестуємо кожен блок сайту, щоб гарантувати Вам безперебійну роботу сайту."
            }
        ]
    },
    "specificServiceProcess": {
        "title": "Процес та його переваги",
        "processEl": [
            {
                "title": "Планування проекту",
                "para": "Під час цього етапу ми визначаємо обсяг проекту, його цілі та терміни, а також збираємо вимоги від зацікавлених сторін і проводимо маркетингове дослідження для кращого розуміння ринку та аудиторії."
            },
            {
                "title": "Дизайн та розробка",
                "para": "На даному етапі дизайнери створюють макети та візуальний дизайн, визначаючи зовнішній вигляд проекту, після чого розробники приступають до реалізації фронтенду та бекенду веб-сайту, забезпечуючи його функціональність та дизайн."
            },
            {
                "title": "Інтеграція контенту",
                "para": "На цьому етапі команда наповнює веб-сайт відповідним контентом, включаючи тексти, зображення, відео та інші медіаресурси, для створення повноцінного інформаційного середовища."
            },
            {
                "title": "Тестування та оптимізація",
                "para": "Відділ з якості виконує тестування функціональності веб-сайту, проводить оптимізацію для пошукових систем (SEO) та гарантує високу продуктивність та безпеку ресурсу."
            },
            {
                "title": "Розгортання та обслуговування",
                "para": "На останньому етапі ми запускаємо веб-сайт, починаємо моніторити аналітику та забезпечуємо постійну підтримку, включаючи оновлення та додатковий розвиток проекту."
            }
        ]
    },
    "specificServiceHero": {
        "title": "Розробка сайтів",
        "buttonText": "Зв’язатися з нами",
        "description": "“Бізнес - це гра партнерства. Ті, хто добре їх формує, досягнуть успіху, а ті, хто ні, залишаться позаду” - Білл Гейтс"
    },
    "howWeWork": {
        "title": "Як ми працюємо?",
        "para": "Ми вивчаємо потреби клієнта, виявляємо всі проблемні питання та визначаємо, як їх усунути. Аналізуємо конкурентів у пошукових результатах та їхні стратегії. Проводимо аудит доступного трафіку на сайті з точки зору джерел та ефективності в пошукових системах.",
        "howWeWorkEl": [
            "Планування проекту",
            "Дизайн та розробка",
            "Інтеграція контенту",
            "Тестування та оптимізація",
            "Розгортання та обслуговування"
        ]
    },
    "ourProjects": {
        "title": "Наші проекти",
        "list": [
            {
                "title": "Редизайн веб-сайту",
                "para": "Якщо придивитися, можна помітити, що ребрендинг став справжнім трендом серед багатьох великих корпорацій. Бренди оновлюють свої логотипи, розробляють нові стратегії та впроваджують сучасні технології, аби зберегти і підвищити свою впізнаваність на ринку.<br /><br />Зміни є єдиною постійною в нашому світі, і це особливо очевидно на прикладі інтернет-технологій. Багато компаній потребують редизайну своїх сайтів з різних причин: одні намагаються випередити конкурентів, інші – зберегти свою аудиторію або привернути нових користувачів.",
                "img": "/images/OurProjects/1.png"
            },
            {
                "title": "Редизайн веб-сайту",
                "para": "Якщо придивитися, можна помітити, що ребрендинг став справжнім трендом серед багатьох великих корпорацій. Бренди оновлюють свої логотипи, розробляють нові стратегії та впроваджують сучасні технології, аби зберегти і підвищити свою впізнаваність на ринку.<br /><br />Зміни є єдиною постійною в нашому світі, і це особливо очевидно на прикладі інтернет-технологій. Багато компаній потребують редизайну своїх сайтів з різних причин: одні намагаються випередити конкурентів, інші – зберегти свою аудиторію або привернути нових користувачів.",
                "img": "/images/OurProjects/2.png"
            }
        ],
        "button": "Переглянути роботу"
    },
    "whatWeUse": {
        "title": "Що ми використовуємо у роботі"
    },
    "commonQuestions": {
        "title": "Поширені запитання та відповіді",
        "para": [
            "Яка вартість розробки веб-сайту?",
            "Чи пропонуєте ви послуги з просування веб-сайту?",
            "Які послуги надає служба підтримки?",
            "Які терміни ви пропонуєте?",
            "Як ви розраховуєте вартість?",
            "Який процес ведення проекту ви пропонуєте?"
        ]
    },
    "marquee": {
        "textItems1": [
            "Лендінг",
            "Багатосторінковий",
            "Інтернет-магазин",
            "2D дизайн",
            "3D моделювання",
            "Розробка логотипів",
            "Google Ads",
            "SEO-просування",
            "UI/UX дизайн",
            "Сайт для доставки",
            "Бізнес сайт",
            "Мобільні застосунки",
            "Лендінг",
            "Багатосторінковий",
            "Інтернет-магазин"
        ],
        "textItems2": [
            "FULLSTACK-INNOVATIONS",
            "FULLSTACK-INNOVATIONS",
            "FULLSTACK-INNOVATIONS",
            "FULLSTACK-INNOVATIONS",
            "FULLSTACK-INNOVATIONS",
            "FULLSTACK-INNOVATIONS",
            "FULLSTACK-INNOVATIONS",
            "FULLSTACK-INNOVATIONS",
            "FULLSTACK-INNOVATIONS",
            "FULLSTACK-INNOVATIONS",
            "FULLSTACK-INNOVATIONS"
        ]
    },
    "modalFeedback": {
        "title": "Відгук або пропозиція щодо роботи",
        "subtitle": "Нам важлива, ваша думка",
        "labels": {
            "name": "Імя",
            "email": "Емейл",
            "message": "Відгук або пропозиція",
            "feedbackType": "Ваша оцінка"
        },
        "errors": {
            "nameRequired": "Заповніть ім'я",
            "emailRequired": "Заповніть пошту",
            "emailInvalid": "Введіть коректний E-mail",
            "feedbackTypeRequired": "Виберіть оцінку",
            "messageRequired": "Заповніть відгук або пропозицію"
        },
        "feedbackOptions": [
            "1 — Погано",
            "2 — Можливо краще",
            "3 — Терпимо",
            "4 — Добре",
            "5 — Відмінно"
        ],
        "submitButton": "Відправити"
    },
    "navPath": {
        "home": "Головна",
        "navPathMap": {
            "about": "Про нас",
            "blog": "Блог",
            "catalog": "Каталог",
            "delivery": "Оплата і доставка",
            "guarantees": "Гарантія",
            "news": "Новини",
            "partnership": "Партнерство",
            "contacts": "Контакти",
            "cart": "Оформлення замовлення",
            "privacy_policy": "Політика конфіденційності",
            "offer_agreement": "Договір Оферти",
            "services": "Послуги",
            "portfolio": "Портфоліо"
        }
    },
    "portfolioTabs": {
        "tabs": [
            "Усе",
            "Веб-дизайн",
            "Веб-розробка",
            "Лого",
            "Бізнес-картки"
        ],
        "readMore": "Перейти на сайт",
        "prevButton": "Попередня сторінка",
        "nextButton": "Наступна сторінка",
        "portfolioData": [
            {
                "id": 1,
                "category": "Веб-дизайн",
                "title": "ВЕБ-ДИЗАЙН ДЛЯ КОМПАНІЇ - ELITY+",
                "image": "/images/blog/1.png"
            },
            {
                "id": 2,
                "category": "Веб-розробка",
                "title": "ВЕБ-ДИЗАЙН ДЛЯ КОМПАНІЇ - PRESSWAVE+",
                "image": "/images/blog/2.png"
            },
            {
                "id": 3,
                "category": "Лого",
                "title": "ВЕБ-ДИЗАЙН ДЛЯ КОМПАНІЇ - ALLEVA+",
                "image": "/images/blog/3.png"
            },
            {
                "id": 4,
                "category": "Веб-розробка",
                "title": "ВЕБ-ДИЗАЙН ДЛЯ КОМПАНІЇ - PRESSWAVE+",
                "image": "/images/blog/4.png"
            },
            {
                "id": 5,
                "category": "Веб-дизайн",
                "title": "ВЕБ-ДИЗАЙН ДЛЯ КОМПАНІЇ - ELITY+",
                "image": "/images/blog/5.png"
            },
            {
                "id": 6,
                "category": "Лого",
                "title": "ВЕБ-ДИЗАЙН ДЛЯ КОМПАНІЇ - ALLEVA+",
                "image": "/images/blog/6.png"
            }
        ]
    },
    "servicesSecond": {
        "items": [
            {
                "svgText": "WEB",
                "subtitle": "Розробка",
                "description": "Наші фахівці мають великий досвід у створенні сучасних веб-сайтів, стильних онлайн-магазинів та інноваційних веб-сервісів."
            },
            {
                "svgText": "SEO",
                "subtitle": "Пошукове просування",
                "description": "Наші експерти ефективно рекламують сайти в Google. Довірте нам свій бренд, і ми гарантуємо успіх вашого онлайн просування."
            },
            {
                "svgText": "PPC",
                "subtitle": "Контекстна реклама",
                "description": "Високопозиційна реклама в Google пошуку для вражаючого успіху вашого бренду! Збільшуйте свою видимість разом з нами."
            },
            {
                "svgText": "BRANDING",
                "subtitle": "Брендинг і дизайн",
                "description": "Візуальний досвід народжується в руках наших фахівців, які об'єднують креативність та високу експертну майстерність в процесі дизайну."
            },
            {
                "svgText": "SUPPORT",
                "subtitle": "Підтримка сайтів",
                "description": "Забезпечуємо технічну підтримку для надійності та оптимальної продуктивності вашого ресурсу. Ваш успіх - це наша мета."
            },
            {
                "svgText": "SMM",
                "subtitle": "Просування в соцмережах",
                "description": "Наша команда має великий досвід у привертанні уваги до відповідного бренду або продукту через різноманітні соціальні платформи."
            },
            {
                "svgText": "Design",
                "subtitle": "2D дизайн",
                "description": "Візуальний досвід народжується в руках наших фахівців, які об'єднують креативність та високу експертну майстерність в процесі дизайну."
            },
            {
                "svgText": "Modeling",
                "subtitle": "3D моделювання",
                "description": "Забезпечуємо технічну підтримку для надійності та оптимальної продуктивності вашого ресурсу. Ваш успіх - це наша мета."
            },
            {
                "svgText": "App",
                "subtitle": "Мобільні застосунки",
                "description": "Наша команда має великий досвід у привертанні уваги до відповідного бренду або продукту через різноманітні соціальні платформи."
            }
        ]
    },
    "workWithUs": {
        "title": "З нами<br />співпрацюють",
        "buttonText": "Залишити відгук",
        "description": "Клієнти довіряють нам свою рекламу із США, Австралії та Європи."
    },
    "technologies": {
        "title": "Технології"
    }
}